tgreet/__init__.py
tgreet/core.py
tgreet-0.1.5.dist-info/LICENSE
tgreet-0.1.5.dist-info/METADATA
tgreet-0.1.5.dist-info/WHEEL
tgreet-0.1.5.dist-info/top_level.txt
tgreet-0.1.5.dist-info/RECORD
