Metadata-Version: 2.1
Name: tgreet
Version: 0.1.5
Summary: Simple greeting library
Author-email: Thendral Magudapathi <thendralmagudapathi@gmail.com>
License: MIT
Project-URL: Homepage, https://github.com/thendralmagudapathi/greet_pip
Requires-Python: >=3.0
License-File: LICENSE
